{
    "actions": [
    {
      "name": "fix_metadata",
      "title": "Fix XMP Metadata"
    },
    {
      "name": "set_title",
      "desc": "Set the document Title metadata by picking text from the first matching structure tag (H1). This aligns metadata with the visible main heading for assistive technologies and preserves any existing Title unless overwrite is enabled.",
      "params": [
        {
          "name": "title_type",
          "value": "1"
        },
        {
          "name": "custom_text",
          "value": ""
        },
        {
          "name": "description_tag",
          "value": "H1"
        },
        {
          "name": "overwrite",
          "value": false
        }
      ],
      "title": "Set Title (From H1 Heading)"
    },
    {
      "name": "set_title",
      "desc": "Set the document Title metadata from the PDF Info dictionary. Use this as a reliable fallback when the tag structure does not contain a suitable heading. Existing Title is preserved unless overwrite is enabled.",
      "params": [
        {
          "name": "title_type",
          "value": "3"
        },
        {
          "name": "custom_text",
          "value": ""
        },
        {
          "name": "description_tag",
          "value": ""
        },
        {
          "name": "overwrite",
          "value": false
        }
      ],
      "title": "Set Title (From Info Dictionary)"
    },
    {
      "name": "set_title",
      "desc": "Set the document Title metadata from the input file name. This provides a deterministic fallback title when neither tag-based detection nor existing Info metadata is suitable. Existing Title is preserved unless overwrite is enabled.",
      "params": [
        {
          "name": "title_type",
          "value": "2"
        },
        {
          "name": "custom_text",
          "value": ""
        },
        {
          "name": "description_tag",
          "value": ""
        },
        {
          "name": "overwrite",
          "value": false
        }
      ],
      "title": "Set Title (From File Name)"
    }, 
    {
      "name": "set_pdf_ua_standard",
      "title": "Set PDF/UA-1 Identifier",
      "desc": "Declare PDF/UA-1 conformance by setting the appropriate PDF/UA identifier in the document metadata.",
      "params": [
        {
          "name": "part_number",
          "value": "1"
        },
        {
          "name": "rev_number",
          "value": "2023"
        }
      ]
    }
    ]
}
